ragchat/__init__.py
ragchat/definitions.py
ragchat/embedding.py
ragchat/llm.py
ragchat/log.py
ragchat/mem.py
ragchat/neo4j.py
ragchat/parser.py
ragchat/pg.py
ragchat/progress.py
ragchat/prompts.py
ragchat/qdrant.py
ragchat/server.py
ragchat/utils.py
ragchat_ai-0.3.1.dist-info/licenses/LICENSE
ragchat_ai-0.3.1.dist-info/METADATA
ragchat_ai-0.3.1.dist-info/WHEEL
ragchat_ai-0.3.1.dist-info/top_level.txt
ragchat_ai-0.3.1.dist-info/RECORD
