Metadata-Version: 2.4
Name: ragchat-ai
Version: 0.3.1
Summary: RagChat transforms unstructured data for LLM interaction.
Home-page: https://github.com/raul3820/ragchat
Author: Raul Ricardo Sanchez
Author-email: ricardo3820@gmail.com
License: MIT
Classifier: Programming Language :: Python :: 3
Classifier: Programming Language :: Python :: 3.11
Classifier: Programming Language :: Python :: 3.12
Classifier: Operating System :: OS Independent
Requires-Python: >=3.11
License-File: LICENSE
Requires-Dist: litellm~=1.68.2
Requires-Dist: asyncpg~=0.30.0
Requires-Dist: neo4j~=5.28.1
Requires-Dist: pydantic-settings~=2.8.1
Requires-Dist: cachetools~=5.5.2
Requires-Dist: rapidfuzz~=3.12.2
Requires-Dist: aiofiles~=24.1.0
Requires-Dist: base58~=2.1.1
Requires-Dist: qdrant-client~=1.14.2
Requires-Dist: scikit-learn~=1.7.0
Requires-Dist: fastembed~=0.7.0
Provides-Extra: dev
Requires-Dist: pytest-asyncio; extra == "dev"
Requires-Dist: ruff; extra == "dev"
Requires-Dist: mypy; extra == "dev"
Requires-Dist: types-cachetools; extra == "dev"
Requires-Dist: types-aiofiles; extra == "dev"
Requires-Dist: asyncpg-stubs; extra == "dev"
Dynamic: author
Dynamic: author-email
Dynamic: classifier
Dynamic: description
Dynamic: description-content-type
Dynamic: home-page
Dynamic: license
Dynamic: license-file
Dynamic: provides-extra
Dynamic: requires-dist
Dynamic: requires-python
Dynamic: summary
